GiN/Galaxyuibuilder.py
GiN/__init__.py
GiN/_frontend.py
GiN/_version.py
GiN/authwidget.py
GiN/display.py
GiN/sessions.py
GiN/settings.py
GiN/taskwidget.py
GiN/util.py
GiN/labextension/package.json
GiN/labextension/static/177.f6f515852dd0b0fa1fe5.js
GiN/labextension/static/397.4ec9ee29b1f4b0e758ae.js
GiN/labextension/static/43.9730d6fd17b18f9dd5dd.js
GiN/labextension/static/480.2090918b32d75e949d92.js
GiN/labextension/static/480.bc927639131aa7f18f61.js
GiN/labextension/static/568.5038907cf529e6743bbc.js
GiN/labextension/static/669.f6c1a35a41f92250172b.js
GiN/labextension/static/794.b78a08265faf48a05bf3.js
GiN/labextension/static/7f7e8263c4c886d64552d3e7dfc0304ed4a56a3636b7f68b95ba1c6be60d1f43.png
GiN/labextension/static/841.0dd93742aae64e6d9e22.js
GiN/labextension/static/841.103ffb7088b14e3be6e9.js
GiN/labextension/static/841.1b5bb0657087d41b8d6d.js
GiN/labextension/static/841.20ccd8d26e3aa72a2a8c.js
GiN/labextension/static/841.23c15f4e4edbe6bdb2b9.js
GiN/labextension/static/841.26474469eb0208cdc765.js
GiN/labextension/static/841.2c06354621c89210799c.js
GiN/labextension/static/841.338675967d8cfc463ace.js
GiN/labextension/static/841.3c77b760b5573796e494.js
GiN/labextension/static/841.45077cb3ffabfe15c1fa.js
GiN/labextension/static/841.4715bd5ad22b23efdfbc.js
GiN/labextension/static/841.47acf4e02c07ff5a70aa.js
GiN/labextension/static/841.4982ccbce6339037bc4c.js
GiN/labextension/static/841.60315d9ea2eccb992054.js
GiN/labextension/static/841.6b8f3c212452cc96f50e.js
GiN/labextension/static/841.706e334aa9b5ebaa0ad8.js
GiN/labextension/static/841.71827ad53f21c85f75f4.js
GiN/labextension/static/841.73b724b516fd141c28d6.js
GiN/labextension/static/841.839060eae76e518050ec.js
GiN/labextension/static/841.8b5bc1d2a097c121d731.js
GiN/labextension/static/841.915c8b1363cfb568047e.js
GiN/labextension/static/841.922eed0322dd9ba7fbb0.js
GiN/labextension/static/841.92eef721f693529aa395.js
GiN/labextension/static/841.94cf4672c9230ba5983f.js
galaxy_gin-0.1.0a9.dist-info/METADATA
galaxy_gin-0.1.0a9.dist-info/WHEEL
galaxy_gin-0.1.0a9.dist-info/top_level.txt
galaxy_gin-0.1.0a9.dist-info/RECORD
